learnable_activation/__init__.py
learnable_activation/__main__.py
learnable_activation/custom_loss.py
learnable_activation/learnable_activation.py
learnable_activation/tabular_densenet.py
learnable_activation-0.0.3.dist-info/METADATA
learnable_activation-0.0.3.dist-info/WHEEL
learnable_activation-0.0.3.dist-info/top_level.txt
learnable_activation-0.0.3.dist-info/RECORD
