Metadata-Version: 2.1
Name: learnable_activation
Version: 0.0.3
Requires-Dist: torch
